swarmauri_certs_self_signed/SelfSignedCertificate.py
swarmauri_certs_self_signed/__init__.py
swarmauri_certs_self_signed-0.2.0.dev4.dist-info/LICENSE
swarmauri_certs_self_signed-0.2.0.dev4.dist-info/METADATA
swarmauri_certs_self_signed-0.2.0.dev4.dist-info/WHEEL
swarmauri_certs_self_signed-0.2.0.dev4.dist-info/entry_points.txt
swarmauri_certs_self_signed-0.2.0.dev4.dist-info/RECORD
